{
  "@context": [
    "https://w3id.org/openbadges/v2",
    "https://w3id.org/blockcerts/v2"
  ],
  "type": "Profile",
  "id": "https://euphonious-fenglisu-342b1d.netlify.app/certificate_verification.json",
  "name": "Google",
  "url": "https://lynk.global/",
  "publicKey": [
    {
      "id": "ecdsa-koblitz-pubkey:0xAa30e9294Fe0018dA70c862b066fa512Dc144b86"
    }
  ],
  "revocationList": "https://euphonious-fenglisu-342b1d.netlify.app/revocations.json",
  "image": "",
  "email": "",
  "description": ""
  }
